Workbook

Sheet DATASET
A1: OrderID | B1: Date | C1: CustomerID | D1: Product | E1: Quantity | F1: UnitPrice | G1: ShippingAddress | H1: PaymentMethod | I1: OrderStatus | J1: TrackingNumber | K1: ItemsInCart | L1: CouponCode | M1: ReferralSource | N1: TotalPrice | O1: Column1 | S1: Quantity | T1: UnitPrice | U1: ItemsInCart | V1: TotalPrice
A2: ORD200000 | B2: 44930 | C2: C72649 | D2: Monitor | E2: 5 | F2: 570.62 | G2: 928 Main St | H2: Debit Card | I2: Shipped | J2: TRK37947903 | K2: 7 | L2: SAVE10 | M2: Instagram | N2: 2853.1 | O2: =IF(OR($N2<EDA_Summary!$B$14,$N2>EDA_Summary!$B$15), "Outlier", "Normal") -> Normal | S2: 5 | T2: 570.62 | U2: 7 | V2: 2853.1
A3: ORD200001 | B3: 45527 | C3: C75739 | D3: Phone | E3: 2 | F3: 151.35 | G3: 823 Main St | H3: Online | I3: Shipped | J3: TRK91186779 | K3: 3 | L3: SAVE10 | M3: Referral | N3: 302.7 | O3: =IF(OR($N3<EDA_Summary!$B$14,$N3>EDA_Summary!$B$15), "Outlier", "Normal") -> Normal | S3: 2 | T3: 151.35 | U3: 3 | V3: 302.7
A4: ORD200002 | B4: 45349 | C4: C81728 | D4: Tablet | E4: 5 | F4: 550.68 | G4: 512 Main St | H4: Credit Card | I4: Cancelled | J4: TRK42903982 | K4: 8 | L4: FREESHIP | M4: Email | N4: 2753.4 | O4: =IF(OR($N4<EDA_Summary!$B$14,$N4>EDA_Summary!$B$15), "Outlier", "Normal") -> Normal | S4: 5 | T4: 550.68 | U4: 8 | V4: 2753.4
A5: ORD200003 | B5: 45214 | C5: C33540 | D5: Chair | E5: 1 | F5: 273.19 | G5: 275 Main St | H5: Debit Card | I5: Returned | J5: TRK62788070 | K5: 5 | L5: SAVE10 | M5: Facebook | N5: 273.19 | O5: =IF(OR($N5<EDA_Summary!$B$14,$N5>EDA_Summary!$B$15), "Outlier", "Normal") -> Normal | S5: 1 | T5: 273.19 | U5: 5 | V5: 273.19
A6: ORD200004 | B6: 45785 | C6: C81840 | D6: Printer | E6: 4 | F6: 626.01 | G6: 668 Main St | H6: Online | I6: Delivered | J6: TRK29241424 | K6: 8 | L6: SAVE10 | M6: Email | N6: 2504.04 | O6: =IF(OR($N6<EDA_Summary!$B$14,$N6>EDA_Summary!$B$15), "Outlier", "Normal") -> Normal | S6: 4 | T6: 626.01 | U6: 8 | V6: 2504.04 | Y6: Quantity | Z6: UnitPrice | AA6: ItemsInCart | AB6: TotalPrice
A7: ORD200005 | B7: 45222 | C7: C37249 | D7: Phone | E7: 2 | F7: 245.86 | G7: 934 Main St | H7: Credit Card | I7: Shipped | J7: TRK72976927 | K7: 4 | L7: SAVE10 | M7: Instagram | N7: 491.72 | O7: =IF(OR($N7<EDA_Summary!$B$14,$N7>EDA_Summary!$B$15), "Outlier", "Normal") -> Normal | S7: 2 | T7: 245.86 | U7: 4 | V7: 491.72 | X7: Quantity | Y7: 1
A8: ORD200006 | B8: 45825 | C8: C83492 | D8: Laptop | E8: 1 | F8: 664.42 | G8: 986 Main St | H8: Gift Card | I8: Returned | J8: TRK96417362 | K8: 6 | L8: SAVE10 | M8: Facebook | N8: 664.42 | O8: =IF(OR($N8<EDA_Summary!$B$14,$N8>EDA_Summary!$B$15), "Outlier", "Normal") -> Normal | S8: 1 | T8: 664.42 | U8: 6 | V8: 664.42 | X8: UnitPrice | Y8: 0.014553341 | Z8: 1
A9: ORD200007 | B9: 45058 | C9: C41460 | D9: Monitor | E9: 5 | F9: 149.55 | G9: 706 Main St | H9: Cash | I9: Shipped | J9: TRK78809193 | K9: 9 | L9: FREESHIP | M9: Facebook | N9: 747.75 | O9: =IF(OR($N9<EDA_Summary!$B$14,$N9>EDA_Summary!$B$15), "Outlier", "Normal") -> Normal | S9: 5 | T9: 149.55 | U9: 9 | V9: 747.75 | X9: ItemsInCart | Y9: 0.65006123 | Z9: 0.00060215368 | AA9: 1
A10: ORD200008 | B10: 45749 | C10: C26817 | D10: Phone | E10: 2 | F10: 134.28 | G10: 904 Main St | H10: Gift Card | I10: Cancelled | J10: TRK61042692 | K10: 2 | L10: NoCoupon | M10: Email | N10: 268.56 | O10: =IF(OR($N10<EDA_Summary!$B$14,$N10>EDA_Summary!$B$15), "Outlier", "Normal") -> Normal | S10: 2 | T10: 134.28 | U10: 2 | V10: 268.56 | X10: TotalPrice | Y10: 0.61525136 | Z10: 0.71708109 | AA10: 0.39254026 | AB10: 1
A11: ORD200009 | B11: 45251 | C11: C31946 | D11: Desk | E11: 4 | F11: 509.38 | G11: 102 Main St | H11: Credit Card | I11: Shipped | J11: TRK33478363 | K11: 6 | L11: SAVE10 | M11: Google | N11: 2037.52 | O11: =IF(OR($N11<EDA_Summary!$B$14,$N11>EDA_Summary!$B$15), "Outlier", "Normal") -> Normal | S11: 4 | T11: 509.38 | U11: 6 | V11: 2037.52
A12: ORD200010 | B12: 45289 | C12: C43443 | D12: Tablet | E12: 5 | F12: 625.97 | G12: 333 Main St | H12: Credit Card | I12: Returned | J12: TRK98859248 | K12: 9 | L12: WINTER15 | M12: Instagram | N12: 3129.85 | O12: =IF(OR($N12<EDA_Summary!$B$14,$N12>EDA_Summary!$B$15), "Outlier", "Normal") -> Normal | S12: 5 | T12: 625.97 | U12: 9 | V12: 3129.85
A13: ORD200011 | B13: 45339 | C13: C93861 | D13: Monitor | E13: 3 | F13: 49.14 | G13: 831 Main St | H13: Online | I13: Returned | J13: TRK48234646 | K13: 7 | L13: SAVE10 | M13: Email | N13: 147.42 | O13: =IF(OR($N13<EDA_Summary!$B$14,$N13>EDA_Summary!$B$15), "Outlier", "Normal") -> Normal | S13: 3 | T13: 49.14 | U13: 7 | V13: 147.42
A14: ORD200012 | B14: 45580 | C14: C38785 | D14: Monitor | E14: 2 | F14: 180.5 | G14: 179 Main St | H14: Debit Card | I14: Pending | J14: TRK20419991 | K14: 6 | L14: FREESHIP | M14: Referral | N14: 361 | O14: =IF(OR($N14<EDA_Summary!$B$14,$N14>EDA_Summary!$B$15), "Outlier", "Normal") -> Normal | S14: 2 | T14: 180.5 | U14: 6 | V14: 361
A15: ORD200013 | B15: 45168 | C15: C88348 | D15: Laptop | E15: 3 | F15: 201.49 | G15: 903 Main St | H15: Credit Card | I15: Returned | J15: TRK81913874 | K15: 4 | L15: FREESHIP | M15: Facebook | N15: 604.47 | O15: =IF(OR($N15<EDA_Summary!$B$14,$N15>EDA_Summary!$B$15), "Outlier", "Normal") -> Normal | S15: 3 | T15: 201.49 | U15: 4 | V15: 604.47
A16: ORD200014 | B16: 45012 | C16: C98474 | D16: Tablet | E16: 2 | F16: 393.33 | G16: 980 Main St | H16: Debit Card | I16: Pending | J16: TRK79186539 | K16: 3 | L16: SAVE10 | M16: Instagram | N16: 786.66 | O16: =IF(OR($N16<EDA_Summary!$B$14,$N16>EDA_Summary!$B$15), "Outlier", "Normal") -> Normal | S16: 2 | T16: 393.33 | U16: 3 | V16: 786.66
A17: ORD200015 | B17: 45124 | C17: C39416 | D17: Printer | E17: 1 | F17: 473.96 | G17: 942 Main St | H17: Cash | I17: Delivered | J17: TRK54930938 | K17: 3 | L17: NoCoupon | M17: Google | N17: 473.96 | O17: =IF(OR($N17<EDA_Summary!$B$14,$N17>EDA_Summary!$B$15), "Outlier", "Normal") -> Normal | S17: 1 | T17: 473.96 | U17: 3 | V17: 473.96
A18: ORD200016 | B18: 44950 | C18: C28976 | D18: Printer | E18: 2 | F18: 533.81 | G18: 914 Main St | H18: Credit Card | I18: Pending | J18: TRK13194259 | K18: 3 | L18: FREESHIP | M18: Email | N18: 1067.62 | O18: =IF(OR($N18<EDA_Summary!$B$14,$N18>EDA_Summary!$B$15), "Outlier", "Normal") -> Normal | S18: 2 | T18: 533.81 | U18: 3 | V18: 1067.62
A19: ORD200017 | B19: 45353 | C19: C60672 | D19: Tablet | E19: 1 | F19: 423.4 | G19: 382 Main St | H19: Debit Card | I19: Shipped | J19: TRK11972116 | K19: 3 | L19: NoCoupon | M19: Referral | N19: 423.4 | O19: =IF(OR($N19<EDA_Summary!$B$14,$N19>EDA_Summary!$B$15), "Outlier", "Normal") -> Normal | S19: 1 | T19: 423.4 | U19: 3 | V19: 423.4
A20: ORD200018 | B20: 45742 | C20: C84329 | D20: Desk | E20: 1 | F20: 431.44 | G20: 891 Main St | H20: Gift Card | I20: Pending | J20: TRK65191045 | K20: 3 | L20: SAVE10 | M20: Facebook | N20: 431.44 | O20: =IF(OR($N20<EDA_Summary!$B$14,$N20>EDA_Summary!$B$15), "Outlier", "Normal") -> Normal | S20: 1 | T20: 431.44 | U20: 3 | V20: 431.44
A21: ORD200019 | B21: 44949 | C21: C14552 | D21: Monitor | E21: 5 | F21: 224 | G21: 273 Main St | H21: Cash | I21: Returned | J21: TRK59101365 | K21: 9 | L21: SAVE10 | M21: Google | N21: 1120 | O21: =IF(OR($N21<EDA_Summary!$B$14,$N21>EDA_Summary!$B$15), "Outlier", "Normal") -> Normal | S21: 5 | T21: 224 | U21: 9 | V21: 1120
A22: ORD200020 | B22: 45054 | C22: C54829 | D22: Chair | E22: 5 | F22: 62.51 | G22: 587 Main St | H22: Cash | I22: Pending | J22: TRK16718651 | K22: 9 | L22: WINTER15 | M22: Instagram | N22: 312.55 | O22: =IF(OR($N22<EDA_Summary!$B$14,$N22>EDA_Summary!$B$15), "Outlier", "Normal") -> Normal | S22: 5 | T22: 62.51 | U22: 9 | V22: 312.55
... A1201: ORD201199 | B1201: 45088 | C1201: C57502 | D1201: Tablet | E1201: 4 | F1201: 560.58 | G1201: 201 Main St | H1201: Gift Card | I1201: Returned | J1201: TRK51116746 | K1201: 6 | L1201: SAVE10 | M1201: Referral | N1201: 2242.32 | O1201: =IF(OR($N1201<EDA_Summary!$B$14,$N1201>EDA_Summary!$B$15), "Outlier", "Normal") -> Normal | S1201: 4 | T1201: 560.58 | U1201: 6 | V1201: 2242.32

Sheet EDA_Summary
A1: TotalPrice - Exploratory Data Analysis
A2: Median (₦823.62) is well below the mean (₦1,053.97), confirming TotalPrice is right-skewed — a few large orders pull the average up. Use median for “typical” order value.
A3: MIN | B3: =MIN(Sheet1[TotalPrice]) -> 11.39
A4: QUARTILE 1 | B4: =_xlfn.QUARTILE.INC(Sheet1[TotalPrice],1) -> 410.52
A5: MEDIAN | B5: =MEDIAN(Sheet1[TotalPrice]) -> 823.615
A6: QUARTILE 3 | B6: =_xlfn.QUARTILE.INC(Sheet1[TotalPrice],3) -> 1578.475
A7: MAX | B7: =MAX(Sheet1[TotalPrice]) -> 3456.4
A8: AVERAGE | B8: =AVERAGE(Sheet1[TotalPrice]) -> 1053.9683
A11: IQR OUTLIER
A12: Orders above ₦3,330.41 are flagged as outliers — 8 in total. Worth a quick manual check to confirm they’re real bulk orders, not data errors.
A13: IQR | B13: =B6-B4 -> 1167.955
A14: LOWER BOUND | B14: =B4-1.5*B13 -> -1341.4125
A15: UPPER BOUND | B15: =B6+1.5*B13 -> 3330.4075
A16: OUTLIER COUNT | B16: 8
A19: Correlation Matrix
A20: TotalPrice correlates strongly with UnitPrice (0.72) and Quantity (0.62), as expected. ItemsInCart shows a weaker link (0.39) — cart size alone doesn’t predict spend.
B21: Quantity | C21: UnitPrice | D21: ItemsInCart | E21: TotalPrice
A22: Quantity | B22: 1
A23: UnitPrice | B23: 0.014553341 | C23: 1
A24: ItemsInCart | B24: 0.65006123 | C24: 0.00060215368 | D24: 1
A25: TotalPrice | B25: 0.61525136 | C25: 0.71708109 | D25: 0.39254026 | E25: 1

Sheet PIVOT TABLES
A1: KPI
A2: Sum of TotalPrice | B2: Sum of Quantity | C2: Count of CustomerID
A3: 1264762 | B3: 3535 | C3: 1200
A5: Payment method prefered by customers | E5: Top 5 Customer
A6: Payment method | B6: Sum of TotalPrice | C6: Count of CustomerID | E6: Customer ID | F6: Sum of TotalPrice | H6: Sales per Coupon code
A7: Online | B7: 262442.94 | C7: 258 | E7: C38840 | F7: 5723.23 | H7: Coupon code | I7: Sum of TotalPrice
A8: Cash | B8: 259786.29 | C8: 246 | E8: C57276 | F8: 3456.4 | H8: FREESHIP | I8: 335036.99
A9: Credit Card | B9: 263847.63 | C9: 234 | E9: C67260 | F9: 3390.8 | H9: NoCoupon | I9: 322401.41
A10: Debit Card | B10: 232361.18 | C10: 232 | E10: C13877 | F10: 3384.9 | H10: SAVE10 | I10: 304840.02
A11: Gift Card | B11: 246323.92 | C11: 230 | E11: C18404 | F11: 3370.2 | H11: WINTER15 | I11: 302483.54
E12: Grand Total | F12: 19325.53
A13: Sales per Year
A14: Year | B14: Sum of TotalPrice | D14: Top 5 Sales per Unit price
A15: 2023 | B15: 552643.24 | D15: Sum of TotalPrice | E15: Unit price
A16: 2024 | B16: 480235.87 | D16: no. | E16: 629.34 | F16: 676.98 | G16: 678.16 | H16: 678.19 | I16: 691.28
A17: 2025 | B17: 231882.85 | D17: 4 | E17: 5034.72
D18: 5 | F18: 3384.9 | G18: 3390.8 | H18: 3390.95 | I18: 3456.4
A19: Sales per Month
A20: Month | B20: Sum of TotalPrice
A21: Jun | B21: 170616.13 | D21: Sales per Product | G21: Sales per OrderStatus
A22: May | B22: 135142.59 | D22: Product | E22: Sum of TotalPrice | G22: OrderStatus | H22: Sum of Quantity | I22: Sum of TotalPrice
A23: Jan | B23: 124313.23 | D23: Chair | E23: 195620.11 | G23: Cancelled | H23: 759 | I23: 276396.21 | J23: =SUM(K23)/SUM($K$23:$K$27) -> 0.21853615 | K23: 276396.21
A24: Mar | B24: 123840.93 | D24: Printer | E24: 195612.61 | G24: Pending | H24: 724 | I24: 256328.15 | J24: =SUM(K24)/SUM($K$23:$K$27) -> 0.20266909 | K24: 256328.15
A25: Feb | B25: 112344.78 | D25: Laptop | E25: 192126.56 | G25: Delivered | H25: 690 | I25: 242600.32 | J25: =SUM(K25)/SUM($K$23:$K$27) -> 0.191815 | K25: 242600.32
A26: Apr | B26: 109186.05 | D26: Tablet | E26: 186568.95 | G26: Returned | H26: 682 | I26: 243277.7 | J26: =SUM(K26)/SUM($K$23:$K$27) -> 0.19235058 | K26: 243277.7
A27: Oct | B27: 89834.82 | D27: Monitor | E27: 175651.41 | G27: Shipped | H27: 680 | I27: 246159.58 | J27: =SUM(K27)/SUM($K$23:$K$27) -> 0.19462918 | K27: 246159.58
A28: Aug | B28: 86343.21 | D28: Desk | E28: 167459.93 | G28: Grand Total | H28: 3535 | I28: 1264762
A29: Jul | B29: 85784.64 | D29: Phone | E29: 151722.39
A30: Dec | B30: 82540.5
A31: Nov | B31: 75493.43
A32: Sep | B32: 69321.65
